README.md
setup.cfg
setup.py
src/ExpdLoggerService/__init__.py
src/ExpdLoggerService/customlogger.py
src/ExpdLoggerService.egg-info/PKG-INFO
src/ExpdLoggerService.egg-info/SOURCES.txt
src/ExpdLoggerService.egg-info/dependency_links.txt
src/ExpdLoggerService.egg-info/requires.txt
src/ExpdLoggerService.egg-info/top_level.txt