Metadata-Version: 1.0
Name: ExpdLoggerService
Version: 0.5.0
Summary: Python Module for customize logger
Home-page: UNKNOWN
Author: greg he
Author-email: greg.he@expeditors.com
License: MIT
Keywords: logger service
Platform: UNKNOWN
